MANIFEST.in
README.txt
setup.py
ipnb/__init__.py
ipnb/importer.py
ipnb/run.py
ipnb/utils.py
ipnb.egg-info/PKG-INFO
ipnb.egg-info/SOURCES.txt
ipnb.egg-info/dependency_links.txt
ipnb.egg-info/top_level.txt
test/test_import.py