Metadata-Version: 1.0
Name: ipnb
Version: 0.1.0
Summary: IPython Notebook code reuse
Home-page: https://github.com/atiasnir/ipnb
Author: Nir Atias
Author-email: rinatias@gmail.com
License: LICENSE.txt
Keywords: ipython notebook code reuse share
Platform: UNKNOWN
